Metadata-Version: 1.0
Name: prepros
Version: 1.0.4
Summary: prepros
Home-page: UNKNOWN
Author: UNKNOWN
Author-email: UNKNOWN
License: UNKNOWN
Platform: UNKNOWN
